PySuperGui/__init__.py
PySuperGui-0.0.5.1.dist-info/METADATA
PySuperGui-0.0.5.1.dist-info/WHEEL
PySuperGui-0.0.5.1.dist-info/top_level.txt
PySuperGui-0.0.5.1.dist-info/RECORD
