Metadata-Version: 2.1
Name: PySuperGui
Version: 0.0.5.1
Summary: This library creates guis in a simpler way using Tkinter
Author: PySuperGui (Aliscreative)
Author-email: <test@test.com>
License: UNKNOWN
Keywords: python,gui,tkinter,UI,Simple Ui,Simple Gui,window
Platform: UNKNOWN
Classifier: Intended Audience :: Developers
Classifier: Programming Language :: Python :: 3
Classifier: Operating System :: Microsoft :: Windows
Classifier: Development Status :: 3 - Alpha
